README.txt
buildout.cfg
setup.py
src/zc/__init__.py
src/zc.rst2.egg-info/PKG-INFO
src/zc.rst2.egg-info/SOURCES.txt
src/zc.rst2.egg-info/dependency_links.txt
src/zc.rst2.egg-info/entry_points.txt
src/zc.rst2.egg-info/namespace_packages.txt
src/zc.rst2.egg-info/requires.txt
src/zc.rst2.egg-info/top_level.txt
src/zc.rst2.egg-info/zip-safe
src/zc/rst2/__init__.py
