Metadata-Version: 1.0
Name: zc.rst2
Version: 0.2
Summary: Script for converting reStructuredText to various formats
Home-page: http://www.python.org/pypi/zc.rst2
Author: Jim Fulton
Author-email: jim@zope.com
License: ZPL 2.1
Keywords: reStructutedText
Platform: UNKNOWN
